codebook/__init__.py
codebook/codebook.py
codebook/codebook_function.py
stata_codebook/__init__.py
stata_codebook/codebook.py
stata_codebook-0.2.0.dist-info/LICENSE.txt
stata_codebook-0.2.0.dist-info/METADATA
stata_codebook-0.2.0.dist-info/WHEEL
stata_codebook-0.2.0.dist-info/top_level.txt
stata_codebook-0.2.0.dist-info/RECORD
