Metadata-Version: 2.1
Name: stata_codebook
Version: 0.2.0
Summary: A Python package for generating comprehensive data summaries and statistics, similar to Stata's codebook command.
Home-page: https://github.com/MohsenAskar
Author: Mohsen Askar
Author-email: ceaser198511@gmail.com
License: MIT
Classifier: Programming Language :: Python :: 3
Classifier: License :: OSI Approved :: MIT License
License-File: LICENSE.txt
Requires-Dist: numpy
Requires-Dist: pandas
Requires-Dist: scipy
